document_ai/__init__.py
document_ai/auth.py
document_ai/cli.py
document_ai/document_ai.py
document_ai/document_ocr.py
document_ai/filesystem/__init__.py
document_ai/filesystem/gcs.py
document_ai/filesystem/s3.py
document_ai/filesystem/url.py
document_ai/utils/__init__.py
document_ai/utils/common_logger.py
document_ai/utils/manager.py
document_ai-0.1.1.dist-info/AUTHORS.rst
document_ai-0.1.1.dist-info/LICENSE
document_ai-0.1.1.dist-info/METADATA
document_ai-0.1.1.dist-info/WHEEL
document_ai-0.1.1.dist-info/entry_points.txt
document_ai-0.1.1.dist-info/top_level.txt
document_ai-0.1.1.dist-info/RECORD
