Metadata-Version: 2.1
Name: document-ai
Version: 0.1.1
Summary: ''
Home-page: https://github.com/PowerCred/document_ai
Author: Shrinivas Deshmukh
Author-email: shrinivas@powercred.io
License: MIT license
Keywords: document_ai
Platform: UNKNOWN
Classifier: Development Status :: 2 - Pre-Alpha
Classifier: Intended Audience :: Developers
Classifier: License :: OSI Approved :: MIT License
Classifier: Natural Language :: English
Classifier: Programming Language :: Python :: 3
Classifier: Programming Language :: Python :: 3.6
Classifier: Programming Language :: Python :: 3.7
Classifier: Programming Language :: Python :: 3.8
Requires-Python: >=3.6
License-File: LICENSE
License-File: AUTHORS.rst
Requires-Dist: aiohttp
Requires-Dist: aiofiles
Requires-Dist: Pillow
Requires-Dist: google-cloud-storage
Requires-Dist: boto3
